opbeat/__init__.py
opbeat/base.py
opbeat_api-0.1.2.dist-info/DESCRIPTION.rst
opbeat_api-0.1.2.dist-info/METADATA
opbeat_api-0.1.2.dist-info/RECORD
opbeat_api-0.1.2.dist-info/WHEEL
opbeat_api-0.1.2.dist-info/metadata.json
opbeat_api-0.1.2.dist-info/top_level.txt
